jaxdecomp/fft.py
jaxdecomp/__init__.py
jaxdecomp/transpose.py
jaxdecomp/typing.py
jaxdecomp/halo.py
jaxdecomp/_src/spmd_ops.py
jaxdecomp/_src/fft_utils.py
jaxdecomp/_src/pencil_utils.py
jaxdecomp/_src/__init__.py
jaxdecomp/_src/error.py
jaxdecomp/_src/cudecomp/fft.py
jaxdecomp/_src/cudecomp/__init__.py
jaxdecomp/_src/cudecomp/transpose.py
jaxdecomp/_src/cudecomp/halo.py
jaxdecomp/_src/jax/fft.py
jaxdecomp/_src/jax/__init__.py
jaxdecomp/_src/jax/transpose.py
jaxdecomp/_src/jax/fftfreq.py
jaxdecomp/_src/jax/halo.py
jaxdecomplib/_jaxdecomp.cpython-310-x86_64-linux-gnu.so
jaxdecomp-0.2.8.dist-info/METADATA
jaxdecomp-0.2.8.dist-info/WHEEL
jaxdecomp-0.2.8.dist-info/RECORD
jaxdecomp-0.2.8.dist-info/licenses/LICENSE
