Metadata-Version: 2.1
Name: jaxdecomp
Version: 0.2.8
Summary: JAX bindings for the cuDecomp library
Author: Wassim Kabalan, Francois Lanusse
License: MIT License
Classifier: Programming Language :: Python :: 3
Classifier: Programming Language :: Python :: 3.10
Classifier: Programming Language :: Python :: 3.11
Classifier: Programming Language :: Python :: 3.12
Classifier: License :: OSI Approved :: MIT License
Classifier: Operating System :: OS Independent
Classifier: Intended Audience :: Developers
Classifier: Intended Audience :: Science/Research
Project-URL: Homepage, https://github.com/DifferentiableUniverseInitiative/jaxDecomp
Requires-Dist: jaxtyping>=0.2.0
Requires-Dist: jax>=0.4.35
Requires-Dist: typing-extensions; python_version < "3.11"
Provides-Extra: test
Requires-Dist: pytest>=8.0.0; extra == "test"
